sagemcom_api/__init__.py
sagemcom_api/client.py
sagemcom_api/const.py
sagemcom_api/enums.py
sagemcom_api/exceptions.py
sagemcom_api/models.py
sagemcom_api-1.4.2.dist-info/LICENSE
sagemcom_api-1.4.2.dist-info/METADATA
sagemcom_api-1.4.2.dist-info/WHEEL
sagemcom_api-1.4.2.dist-info/RECORD
