Metadata-Version: 2.3
Name: sagemcom_api
Version: 1.4.2
Summary: Python client to interact with SagemCom F@st routers via internal API's.
License: MIT
Keywords: sagemcom,f@st
Author: Mick Vleeshouwer
Author-email: mick@imick.nl
Requires-Python: >=3.9,<4.0
Classifier: License :: OSI Approved :: MIT License
Classifier: Programming Language :: Python :: 3
Classifier: Programming Language :: Python :: 3.9
Classifier: Programming Language :: Python :: 3.10
Classifier: Programming Language :: Python :: 3.11
Classifier: Programming Language :: Python :: 3.12
Classifier: Programming Language :: Python :: 3.13
Requires-Dist: aiohttp (>=3.7.3,<4.0.0)
Requires-Dist: backoff (>=1.10.0,<3.0)
Requires-Dist: backports-strenum (>=1.3.1,<2.0.0) ; python_version < "3.11"
Requires-Dist: pyhumps (>=3.0.2,<4.0.0)
Project-URL: Bug Tracker, https://github.com/iMicknl/python-sagemcom-api/issues
Project-URL: Homepage, https://github.com/iMicknl/python-sagemcom-api
Project-URL: Repository, https://github.com/iMicknl/python-sagemcom-api
